vycro/__about__.py
vycro/__init__.py
vycro/wrappers.py
vycro-1.0.0.dist-info/DESCRIPTION.rst
vycro-1.0.0.dist-info/METADATA
vycro-1.0.0.dist-info/RECORD
vycro-1.0.0.dist-info/WHEEL
vycro-1.0.0.dist-info/metadata.json
vycro-1.0.0.dist-info/top_level.txt
