Metadata-Version: 2.0
Name: vycro
Version: 1.0.0
Summary: VBA macro wrapper for Python to be used with Microsoft Excel.
Home-page: https://github.com/gannon93/vycro
Author: Zach Gannon
Author-email: zachgannon93@gmail.com
License: MIT
Keywords: VBA,macros,Excel
Platform: UNKNOWN
Classifier: Natural Language :: English
Classifier: License :: OSI Approved :: MIT License
Classifier: Programming Language :: Python :: 2
Classifier: Programming Language :: Python :: 2.7
Classifier: Programming Language :: Python :: 3
Classifier: Programming Language :: Python :: 3.4
Classifier: Topic :: Software Development :: Libraries :: Python Modules
Requires-Dist: pypiwin32
